mesa2_preprocessing/__init__.py
mesa2_preprocessing/operations.py
mesa2_preprocessing-0.4.0.dist-info/LICENSE
mesa2_preprocessing-0.4.0.dist-info/METADATA
mesa2_preprocessing-0.4.0.dist-info/WHEEL
mesa2_preprocessing-0.4.0.dist-info/top_level.txt
mesa2_preprocessing-0.4.0.dist-info/RECORD
