Metadata-Version: 2.1
Name: mesa2-preprocessing
Version: 0.4.0
Summary: A tool for pre-processing MESA2.0 measurement data
Author: Nadir Nadirov
Author-email: nadirnadirov1999@gmail.com
Classifier: Development Status :: 3 - Alpha
Classifier: Intended Audience :: Developers
Classifier: License :: OSI Approved :: MIT License
Classifier: Natural Language :: English
Classifier: Operating System :: OS Independent
Classifier: Programming Language :: Python :: 3
Classifier: Programming Language :: Python :: 3.8
Classifier: Programming Language :: Python :: 3.9
Classifier: Programming Language :: Python :: 3.10
Classifier: Topic :: Scientific/Engineering :: Visualization
Requires-Python: >=3.8
License-File: LICENSE
Requires-Dist: pandas >=1.0
Requires-Dist: numpy >=1.18
Requires-Dist: nptdms >=0.25
Requires-Dist: pyarrow >=4.0
Requires-Dist: fastparquet >=0.6
